[{"export_type":"FortQuestItemDefinition","QuestType":"EFortQuestType::AthenaChallengeBundleQuest","bShouldDisplayOverallQuestInformation":true,"bAthenaMustCompleteInSingleMatch":true,"bIncludedInCategories":false,"ObjectiveCompletionCount":2,"Rewards":[{"ItemPrimaryAssetId":{"PrimaryAssetType":{"Name":"AccountResource"},"PrimaryAssetName":"athenabattlestar"},"Quantity":5}],"Objectives":[{"BackendName":"battlepass_ringdoorbell_differenthouses_poi","ObjectiveStatHandle":{"DataTable":"AthenaObjectiveStatTable","RowName":"interact_athena_doorbell_anarchyacres"},"AlternativeStatHandles":[],"ItemEvent":"EFortQuestObjectiveItemEvent::Max_None","bHidden":false,"bRequirePrimaryMissionCompletion":false,"bCanProgressInZone":true,"bDisplayDynamicAnnouncementUpdate":false,"DynamicStatusUpdateType":"EObjectiveStatusUpdateType::Always","LinkVaultTab":"EFortInventoryFilter::Max_None","LinkToItemManagement":"EFortFrontendInventoryFilter::Max_None","ItemReference":{"asset_path_name":"None","sub_path_string":""},"ItemTemplateIdOverride":"","LinkSquadID":"None","LinkSquadIndex":0,"Description":"Ring a doorbell in different named locations in a single match","HudShortDescription":"Ring a doorbell in different named locations in a single match","HudIcon":{"asset_path_name":"None","sub_path_string":""},"Count":1,"Stage":-1,"DynamicStatusUpdatePercentInterval":25,"DynamicUpdateCompletionDelay":0.0,"ScriptedAction":{"asset_path_name":"None","sub_path_string":""}},{"BackendName":"battlepass_ringdoorbell_differenthouses_poi","ObjectiveStatHandle":{"DataTable":"AthenaObjectiveStatTable","RowName":"interact_athena_doorbell_dustydivot"},"AlternativeStatHandles":[],"ItemEvent":"EFortQuestObjectiveItemEvent::Max_None","bHidden":false,"bRequirePrimaryMissionCompletion":false,"bCanProgressInZone":true,"bDisplayDynamicAnnouncementUpdate":false,"DynamicStatusUpdateType":"EObjectiveStatusUpdateType::Always","LinkVaultTab":"EFortInventoryFilter::Max_None","LinkToItemManagement":"EFortFrontendInventoryFilter::Max_None","ItemReference":{"asset_path_name":"None","sub_path_string":""},"ItemTemplateIdOverride":"","LinkSquadID":"None","LinkSquadIndex":0,"Description":"Ring a doorbell in different named locations in a single match","HudShortDescription":"Ring a doorbell in different named locations in a single match","HudIcon":{"asset_path_name":"None","sub_path_string":""},"Count":1,"Stage":-1,"DynamicStatusUpdatePercentInterval":25,"DynamicUpdateCompletionDelay":0.0,"ScriptedAction":{"asset_path_name":"None","sub_path_string":""}},{"BackendName":"battlepass_ringdoorbell_differenthouses_poi","ObjectiveStatHandle":{"DataTable":"AthenaObjectiveStatTable","RowName":"interact_athena_doorbell_fatalfields"},"AlternativeStatHandles":[],"ItemEvent":"EFortQuestObjectiveItemEvent::Max_None","bHidden":false,"bRequirePrimaryMissionCompletion":false,"bCanProgressInZone":true,"bDisplayDynamicAnnouncementUpdate":false,"DynamicStatusUpdateType":"EObjectiveStatusUpdateType::Always","LinkVaultTab":"EFortInventoryFilter::Max_None","LinkToItemManagement":"EFortFrontendInventoryFilter::Max_None","ItemReference":{"asset_path_name":"None","sub_path_string":""},"ItemTemplateIdOverride":"","LinkSquadID":"None","LinkSquadIndex":0,"Description":"Ring a doorbell in different named locations in a single match","HudShortDescription":"Ring a doorbell in different named locations in a single match","HudIcon":{"asset_path_name":"None","sub_path_string":""},"Count":1,"Stage":-1,"DynamicStatusUpdatePercentInterval":25,"DynamicUpdateCompletionDelay":0.0,"ScriptedAction":{"asset_path_name":"None","sub_path_string":""}},{"BackendName":"battlepass_ringdoorbell_differenthouses_poi","ObjectiveStatHandle":{"DataTable":"AthenaObjectiveStatTable","RowName":"interact_athena_doorbell_flushfactory"},"AlternativeStatHandles":[],"ItemEvent":"EFortQuestObjectiveItemEvent::Max_None","bHidden":false,"bRequirePrimaryMissionCompletion":false,"bCanProgressInZone":true,"bDisplayDynamicAnnouncementUpdate":false,"DynamicStatusUpdateType":"EObjectiveStatusUpdateType::Always","LinkVaultTab":"EFortInventoryFilter::Max_None","LinkToItemManagement":"EFortFrontendInventoryFilter::Max_None","ItemReference":{"asset_path_name":"None","sub_path_string":""},"ItemTemplateIdOverride":"","LinkSquadID":"None","LinkSquadIndex":0,"Description":"Ring a doorbell in different named locations in a single match","HudShortDescription":"Ring a doorbell in different named locations in a single match","HudIcon":{"asset_path_name":"None","sub_path_string":""},"Count":1,"Stage":-1,"DynamicStatusUpdatePercentInterval":25,"DynamicUpdateCompletionDelay":0.0,"ScriptedAction":{"asset_path_name":"None","sub_path_string":""}},{"BackendName":"battlepass_ringdoorbell_differenthouses_poi","ObjectiveStatHandle":{"DataTable":"AthenaObjectiveStatTable","RowName":"interact_athena_doorbell_frostyflights"},"AlternativeStatHandles":[],"ItemEvent":"EFortQuestObjectiveItemEvent::Max_None","bHidden":false,"bRequirePrimaryMissionCompletion":false,"bCanProgressInZone":true,"bDisplayDynamicAnnouncementUpdate":false,"DynamicStatusUpdateType":"EObjectiveStatusUpdateType::Always","LinkVaultTab":"EFortInventoryFilter::Max_None","LinkToItemManagement":"EFortFrontendInventoryFilter::Max_None","ItemReference":{"asset_path_name":"None","sub_path_string":""},"ItemTemplateIdOverride":"","LinkSquadID":"None","LinkSquadIndex":0,"Description":"Ring a doorbell in different named locations in a single match","HudShortDescription":"Ring a doorbell in different named locations in a single match","HudIcon":{"asset_path_name":"None","sub_path_string":""},"Count":1,"Stage":-1,"DynamicStatusUpdatePercentInterval":25,"DynamicUpdateCompletionDelay":0.0,"ScriptedAction":{"asset_path_name":"None","sub_path_string":""}},{"BackendName":"battlepass_ringdoorbell_differenthouses_poi","ObjectiveStatHandle":{"DataTable":"AthenaObjectiveStatTable","RowName":"interact_athena_doorbell_greasygrove"},"AlternativeStatHandles":[],"ItemEvent":"EFortQuestObjectiveItemEvent::Max_None","bHidden":false,"bRequirePrimaryMissionCompletion":false,"bCanProgressInZone":true,"bDisplayDynamicAnnouncementUpdate":false,"DynamicStatusUpdateType":"EObjectiveStatusUpdateType::Always","LinkVaultTab":"EFortInventoryFilter::Max_None","LinkToItemManagement":"EFortFrontendInventoryFilter::Max_None","ItemReference":{"asset_path_name":"None","sub_path_string":""},"ItemTemplateIdOverride":"","LinkSquadID":"None","LinkSquadIndex":0,"Description":"Ring a doorbell in different named locations in a single match","HudShortDescription":"Ring a doorbell in different named locations in a single match","HudIcon":{"asset_path_name":"None","sub_path_string":""},"Count":1,"Stage":-1,"DynamicStatusUpdatePercentInterval":25,"DynamicUpdateCompletionDelay":0.0,"ScriptedAction":{"asset_path_name":"None","sub_path_string":""}},{"BackendName":"battlepass_ringdoorbell_differenthouses_poi","ObjectiveStatHandle":{"DataTable":"AthenaObjectiveStatTable","RowName":"interact_athena_doorbell_happyhamlet"},"AlternativeStatHandles":[],"ItemEvent":"EFortQuestObjectiveItemEvent::Max_None","bHidden":false,"bRequirePrimaryMissionCompletion":false,"bCanProgressInZone":true,"bDisplayDynamicAnnouncementUpdate":false,"DynamicStatusUpdateType":"EObjectiveStatusUpdateType::Always","LinkVaultTab":"EFortInventoryFilter::Max_None","LinkToItemManagement":"EFortFrontendInventoryFilter::Max_None","ItemReference":{"asset_path_name":"None","sub_path_string":""},"ItemTemplateIdOverride":"","LinkSquadID":"None","LinkSquadIndex":0,"Description":"Ring a doorbell in different named locations in a single match","HudShortDescription":"Ring a doorbell in different named locations in a single match","HudIcon":{"asset_path_name":"None","sub_path_string":""},"Count":1,"Stage":-1,"DynamicStatusUpdatePercentInterval":25,"DynamicUpdateCompletionDelay":0.0,"ScriptedAction":{"asset_path_name":"None","sub_path_string":""}},{"BackendName":"battlepass_ringdoorbell_differenthouses_poi","ObjectiveStatHandle":{"DataTable":"AthenaObjectiveStatTable","RowName":"interact_athena_doorbell_hauntedhills"},"AlternativeStatHandles":[],"ItemEvent":"EFortQuestObjectiveItemEvent::Max_None","bHidden":false,"bRequirePrimaryMissionCompletion":false,"bCanProgressInZone":true,"bDisplayDynamicAnnouncementUpdate":false,"DynamicStatusUpdateType":"EObjectiveStatusUpdateType::Always","LinkVaultTab":"EFortInventoryFilter::Max_None","LinkToItemManagement":"EFortFrontendInventoryFilter::Max_None","ItemReference":{"asset_path_name":"None","sub_path_string":""},"ItemTemplateIdOverride":"","LinkSquadID":"None","LinkSquadIndex":0,"Description":"Ring a doorbell in different named locations in a single match","HudShortDescription":"Ring a doorbell in different named locations in a single match","HudIcon":{"asset_path_name":"None","sub_path_string":""},"Count":1,"Stage":-1,"DynamicStatusUpdatePercentInterval":25,"DynamicUpdateCompletionDelay":0.0,"ScriptedAction":{"asset_path_name":"None","sub_path_string":""}},{"BackendName":"battlepass_ringdoorbell_differenthouses_poi","ObjectiveStatHandle":{"DataTable":"AthenaObjectiveStatTable","RowName":"interact_athena_doorbell_junkjunction"},"AlternativeStatHandles":[],"ItemEvent":"EFortQuestObjectiveItemEvent::Max_None","bHidden":false,"bRequirePrimaryMissionCompletion":false,"bCanProgressInZone":true,"bDisplayDynamicAnnouncementUpdate":false,"DynamicStatusUpdateType":"EObjectiveStatusUpdateType::Always","LinkVaultTab":"EFortInventoryFilter::Max_None","LinkToItemManagement":"EFortFrontendInventoryFilter::Max_None","ItemReference":{"asset_path_name":"None","sub_path_string":""},"ItemTemplateIdOverride":"","LinkSquadID":"None","LinkSquadIndex":0,"Description":"Ring a doorbell in different named locations in a single match","HudShortDescription":"Ring a doorbell in different named locations in a single match","HudIcon":{"asset_path_name":"None","sub_path_string":""},"Count":1,"Stage":-1,"DynamicStatusUpdatePercentInterval":25,"DynamicUpdateCompletionDelay":0.0,"ScriptedAction":{"asset_path_name":"None","sub_path_string":""}},{"BackendName":"battlepass_ringdoorbell_differenthouses_poi","ObjectiveStatHandle":{"DataTable":"AthenaObjectiveStatTable","RowName":"interact_athena_doorbell_lazylinks"},"AlternativeStatHandles":[],"ItemEvent":"EFortQuestObjectiveItemEvent::Max_None","bHidden":false,"bRequirePrimaryMissionCompletion":false,"bCanProgressInZone":true,"bDisplayDynamicAnnouncementUpdate":false,"DynamicStatusUpdateType":"EObjectiveStatusUpdateType::Always","LinkVaultTab":"EFortInventoryFilter::Max_None","LinkToItemManagement":"EFortFrontendInventoryFilter::Max_None","ItemReference":{"asset_path_name":"None","sub_path_string":""},"ItemTemplateIdOverride":"","LinkSquadID":"None","LinkSquadIndex":0,"Description":"Ring a doorbell in different named locations in a single match","HudShortDescription":"Ring a doorbell in different named locations in a single match","HudIcon":{"asset_path_name":"None","sub_path_string":""},"Count":1,"Stage":-1,"DynamicStatusUpdatePercentInterval":25,"DynamicUpdateCompletionDelay":0.0,"ScriptedAction":{"asset_path_name":"None","sub_path_string":""}},{"BackendName":"battlepass_ringdoorbell_differenthouses_poi","ObjectiveStatHandle":{"DataTable":"AthenaObjectiveStatTable","RowName":"interact_athena_doorbell_lonelylodge"},"AlternativeStatHandles":[],"ItemEvent":"EFortQuestObjectiveItemEvent::Max_None","bHidden":false,"bRequirePrimaryMissionCompletion":false,"bCanProgressInZone":true,"bDisplayDynamicAnnouncementUpdate":false,"DynamicStatusUpdateType":"EObjectiveStatusUpdateType::Always","LinkVaultTab":"EFortInventoryFilter::Max_None","LinkToItemManagement":"EFortFrontendInventoryFilter::Max_None","ItemReference":{"asset_path_name":"None","sub_path_string":""},"ItemTemplateIdOverride":"","LinkSquadID":"None","LinkSquadIndex":0,"Description":"Ring a doorbell in different named locations in a single match","HudShortDescription":"Ring a doorbell in different named locations in a single match","HudIcon":{"asset_path_name":"None","sub_path_string":""},"Count":1,"Stage":-1,"DynamicStatusUpdatePercentInterval":25,"DynamicUpdateCompletionDelay":0.0,"ScriptedAction":{"asset_path_name":"None","sub_path_string":""}},{"BackendName":"battlepass_ringdoorbell_differenthouses_poi","ObjectiveStatHandle":{"DataTable":"AthenaObjectiveStatTable","RowName":"interact_athena_doorbell_lootlake"},"AlternativeStatHandles":[],"ItemEvent":"EFortQuestObjectiveItemEvent::Max_None","bHidden":false,"bRequirePrimaryMissionCompletion":false,"bCanProgressInZone":true,"bDisplayDynamicAnnouncementUpdate":false,"DynamicStatusUpdateType":"EObjectiveStatusUpdateType::Always","LinkVaultTab":"EFortInventoryFilter::Max_None","LinkToItemManagement":"EFortFrontendInventoryFilter::Max_None","ItemReference":{"asset_path_name":"None","sub_path_string":""},"ItemTemplateIdOverride":"","LinkSquadID":"None","LinkSquadIndex":0,"Description":"Ring a doorbell in different named locations in a single match","HudShortDescription":"Ring a doorbell in different named locations in a single match","HudIcon":{"asset_path_name":"None","sub_path_string":""},"Count":1,"Stage":-1,"DynamicStatusUpdatePercentInterval":25,"DynamicUpdateCompletionDelay":0.0,"ScriptedAction":{"asset_path_name":"None","sub_path_string":""}},{"BackendName":"battlepass_ringdoorbell_differenthouses_poi","ObjectiveStatHandle":{"DataTable":"AthenaObjectiveStatTable","RowName":"interact_athena_doorbell_luckylanding"},"AlternativeStatHandles":[],"ItemEvent":"EFortQuestObjectiveItemEvent::Max_None","bHidden":false,"bRequirePrimaryMissionCompletion":false,"bCanProgressInZone":true,"bDisplayDynamicAnnouncementUpdate":false,"DynamicStatusUpdateType":"EObjectiveStatusUpdateType::Always","LinkVaultTab":"EFortInventoryFilter::Max_None","LinkToItemManagement":"EFortFrontendInventoryFilter::Max_None","ItemReference":{"asset_path_name":"None","sub_path_string":""},"ItemTemplateIdOverride":"","LinkSquadID":"None","LinkSquadIndex":0,"Description":"Ring a doorbell in different named locations in a single match","HudShortDescription":"Ring a doorbell in different named locations in a single match","HudIcon":{"asset_path_name":"None","sub_path_string":""},"Count":1,"Stage":-1,"DynamicStatusUpdatePercentInterval":25,"DynamicUpdateCompletionDelay":0.0,"ScriptedAction":{"asset_path_name":"None","sub_path_string":""}},{"BackendName":"battlepass_ringdoorbell_differenthouses_poi","ObjectiveStatHandle":{"DataTable":"AthenaObjectiveStatTable","RowName":"interact_athena_doorbell_moistymire"},"AlternativeStatHandles":[],"ItemEvent":"EFortQuestObjectiveItemEvent::Max_None","bHidden":false,"bRequirePrimaryMissionCompletion":false,"bCanProgressInZone":true,"bDisplayDynamicAnnouncementUpdate":false,"DynamicStatusUpdateType":"EObjectiveStatusUpdateType::Always","LinkVaultTab":"EFortInventoryFilter::Max_None","LinkToItemManagement":"EFortFrontendInventoryFilter::Max_None","ItemReference":{"asset_path_name":"None","sub_path_string":""},"ItemTemplateIdOverride":"","LinkSquadID":"None","LinkSquadIndex":0,"Description":"Ring a doorbell in different named locations in a single match","HudShortDescription":"Ring a doorbell in different named locations in a single match","HudIcon":{"asset_path_name":"None","sub_path_string":""},"Count":1,"Stage":-1,"DynamicStatusUpdatePercentInterval":25,"DynamicUpdateCompletionDelay":0.0,"ScriptedAction":{"asset_path_name":"None","sub_path_string":""}},{"BackendName":"battlepass_ringdoorbell_differenthouses_poi","ObjectiveStatHandle":{"DataTable":"AthenaObjectiveStatTable","RowName":"interact_athena_doorbell_paradisepalms"},"AlternativeStatHandles":[],"ItemEvent":"EFortQuestObjectiveItemEvent::Max_None","bHidden":false,"bRequirePrimaryMissionCompletion":false,"bCanProgressInZone":true,"bDisplayDynamicAnnouncementUpdate":false,"DynamicStatusUpdateType":"EObjectiveStatusUpdateType::Always","LinkVaultTab":"EFortInventoryFilter::Max_None","LinkToItemManagement":"EFortFrontendInventoryFilter::Max_None","ItemReference":{"asset_path_name":"None","sub_path_string":""},"ItemTemplateIdOverride":"","LinkSquadID":"None","LinkSquadIndex":0,"Description":"Ring a doorbell in different named locations in a single match","HudShortDescription":"Ring a doorbell in different named locations in a single match","HudIcon":{"asset_path_name":"None","sub_path_string":""},"Count":1,"Stage":-1,"DynamicStatusUpdatePercentInterval":25,"DynamicUpdateCompletionDelay":0.0,"ScriptedAction":{"asset_path_name":"None","sub_path_string":""}},{"BackendName":"battlepass_ringdoorbell_differenthouses_poi","ObjectiveStatHandle":{"DataTable":"AthenaObjectiveStatTable","RowName":"interact_athena_doorbell_pleasantpark"},"AlternativeStatHandles":[],"ItemEvent":"EFortQuestObjectiveItemEvent::Max_None","bHidden":false,"bRequirePrimaryMissionCompletion":false,"bCanProgressInZone":true,"bDisplayDynamicAnnouncementUpdate":false,"DynamicStatusUpdateType":"EObjectiveStatusUpdateType::Always","LinkVaultTab":"EFortInventoryFilter::Max_None","LinkToItemManagement":"EFortFrontendInventoryFilter::Max_None","ItemReference":{"asset_path_name":"None","sub_path_string":""},"ItemTemplateIdOverride":"","LinkSquadID":"None","LinkSquadIndex":0,"Description":"Ring a doorbell in different named locations in a single match","HudShortDescription":"Ring a doorbell in different named locations in a single match","HudIcon":{"asset_path_name":"None","sub_path_string":""},"Count":1,"Stage":-1,"DynamicStatusUpdatePercentInterval":25,"DynamicUpdateCompletionDelay":0.0,"ScriptedAction":{"asset_path_name":"None","sub_path_string":""}},{"BackendName":"battlepass_ringdoorbell_differenthouses_poi","ObjectiveStatHandle":{"DataTable":"AthenaObjectiveStatTable","RowName":"interact_athena_doorbell_polarpeak"},"AlternativeStatHandles":[],"ItemEvent":"EFortQuestObjectiveItemEvent::Max_None","bHidden":false,"bRequirePrimaryMissionCompletion":false,"bCanProgressInZone":true,"bDisplayDynamicAnnouncementUpdate":false,"DynamicStatusUpdateType":"EObjectiveStatusUpdateType::Always","LinkVaultTab":"EFortInventoryFilter::Max_None","LinkToItemManagement":"EFortFrontendInventoryFilter::Max_None","ItemReference":{"asset_path_name":"None","sub_path_string":""},"ItemTemplateIdOverride":"","LinkSquadID":"None","LinkSquadIndex":0,"Description":"Ring a doorbell in different named locations in a single match","HudShortDescription":"Ring a doorbell in different named locations in a single match","HudIcon":{"asset_path_name":"None","sub_path_string":""},"Count":1,"Stage":-1,"DynamicStatusUpdatePercentInterval":25,"DynamicUpdateCompletionDelay":0.0,"ScriptedAction":{"asset_path_name":"None","sub_path_string":""}},{"BackendName":"battlepass_ringdoorbell_differenthouses_poi","ObjectiveStatHandle":{"DataTable":"AthenaObjectiveStatTable","RowName":"interact_athena_doorbell_retailrow"},"AlternativeStatHandles":[],"ItemEvent":"EFortQuestObjectiveItemEvent::Max_None","bHidden":false,"bRequirePrimaryMissionCompletion":false,"bCanProgressInZone":true,"bDisplayDynamicAnnouncementUpdate":false,"DynamicStatusUpdateType":"EObjectiveStatusUpdateType::Always","LinkVaultTab":"EFortInventoryFilter::Max_None","LinkToItemManagement":"EFortFrontendInventoryFilter::Max_None","ItemReference":{"asset_path_name":"None","sub_path_string":""},"ItemTemplateIdOverride":"","LinkSquadID":"None","LinkSquadIndex":0,"Description":"Ring a doorbell in different named locations in a single match","HudShortDescription":"Ring a doorbell in different named locations in a single match","HudIcon":{"asset_path_name":"None","sub_path_string":""},"Count":1,"Stage":-1,"DynamicStatusUpdatePercentInterval":25,"DynamicUpdateCompletionDelay":0.0,"ScriptedAction":{"asset_path_name":"None","sub_path_string":""}},{"BackendName":"battlepass_ringdoorbell_differenthouses_poi","ObjectiveStatHandle":{"DataTable":"AthenaObjectiveStatTable","RowName":"interact_athena_doorbell_riskyreels"},"AlternativeStatHandles":[],"ItemEvent":"EFortQuestObjectiveItemEvent::Max_None","bHidden":false,"bRequirePrimaryMissionCompletion":false,"bCanProgressInZone":true,"bDisplayDynamicAnnouncementUpdate":false,"DynamicStatusUpdateType":"EObjectiveStatusUpdateType::Always","LinkVaultTab":"EFortInventoryFilter::Max_None","LinkToItemManagement":"EFortFrontendInventoryFilter::Max_None","ItemReference":{"asset_path_name":"None","sub_path_string":""},"ItemTemplateIdOverride":"","LinkSquadID":"None","LinkSquadIndex":0,"Description":"Ring a doorbell in different named locations in a single match","HudShortDescription":"Ring a doorbell in different named locations in a single match","HudIcon":{"asset_path_name":"None","sub_path_string":""},"Count":1,"Stage":-1,"DynamicStatusUpdatePercentInterval":25,"DynamicUpdateCompletionDelay":0.0,"ScriptedAction":{"asset_path_name":"None","sub_path_string":""}},{"BackendName":"battlepass_ringdoorbell_differenthouses_poi","ObjectiveStatHandle":{"DataTable":"AthenaObjectiveStatTable","RowName":"interact_athena_doorbell_saltysprings"},"AlternativeStatHandles":[],"ItemEvent":"EFortQuestObjectiveItemEvent::Max_None","bHidden":false,"bRequirePrimaryMissionCompletion":false,"bCanProgressInZone":true,"bDisplayDynamicAnnouncementUpdate":false,"DynamicStatusUpdateType":"EObjectiveStatusUpdateType::Always","LinkVaultTab":"EFortInventoryFilter::Max_None","LinkToItemManagement":"EFortFrontendInventoryFilter::Max_None","ItemReference":{"asset_path_name":"None","sub_path_string":""},"ItemTemplateIdOverride":"","LinkSquadID":"None","LinkSquadIndex":0,"Description":"Ring a doorbell in different named locations in a single match","HudShortDescription":"Ring a doorbell in different named locations in a single match","HudIcon":{"asset_path_name":"None","sub_path_string":""},"Count":1,"Stage":-1,"DynamicStatusUpdatePercentInterval":25,"DynamicUpdateCompletionDelay":0.0,"ScriptedAction":{"asset_path_name":"None","sub_path_string":""}},{"BackendName":"battlepass_ringdoorbell_differenthouses_poi","ObjectiveStatHandle":{"DataTable":"AthenaObjectiveStatTable","RowName":"interact_athena_doorbell_shiftyshafts"},"AlternativeStatHandles":[],"ItemEvent":"EFortQuestObjectiveItemEvent::Max_None","bHidden":false,"bRequirePrimaryMissionCompletion":false,"bCanProgressInZone":true,"bDisplayDynamicAnnouncementUpdate":false,"DynamicStatusUpdateType":"EObjectiveStatusUpdateType::Always","LinkVaultTab":"EFortInventoryFilter::Max_None","LinkToItemManagement":"EFortFrontendInventoryFilter::Max_None","ItemReference":{"asset_path_name":"None","sub_path_string":""},"ItemTemplateIdOverride":"","LinkSquadID":"None","LinkSquadIndex":0,"Description":"Ring a doorbell in different named locations in a single match","HudShortDescription":"Ring a doorbell in different named locations in a single match","HudIcon":{"asset_path_name":"None","sub_path_string":""},"Count":1,"Stage":-1,"DynamicStatusUpdatePercentInterval":25,"DynamicUpdateCompletionDelay":0.0,"ScriptedAction":{"asset_path_name":"None","sub_path_string":""}},{"BackendName":"battlepass_ringdoorbell_differenthouses_poi","ObjectiveStatHandle":{"DataTable":"AthenaObjectiveStatTable","RowName":"interact_athena_doorbell_snobbyshores"},"AlternativeStatHandles":[],"ItemEvent":"EFortQuestObjectiveItemEvent::Max_None","bHidden":false,"bRequirePrimaryMissionCompletion":false,"bCanProgressInZone":true,"bDisplayDynamicAnnouncementUpdate":false,"DynamicStatusUpdateType":"EObjectiveStatusUpdateType::Always","LinkVaultTab":"EFortInventoryFilter::Max_None","LinkToItemManagement":"EFortFrontendInventoryFilter::Max_None","ItemReference":{"asset_path_name":"None","sub_path_string":""},"ItemTemplateIdOverride":"","LinkSquadID":"None","LinkSquadIndex":0,"Description":"Ring a doorbell in different named locations in a single match","HudShortDescription":"Ring a doorbell in different named locations in a single match","HudIcon":{"asset_path_name":"None","sub_path_string":""},"Count":1,"Stage":-1,"DynamicStatusUpdatePercentInterval":25,"DynamicUpdateCompletionDelay":0.0,"ScriptedAction":{"asset_path_name":"None","sub_path_string":""}},{"BackendName":"battlepass_ringdoorbell_differenthouses_poi","ObjectiveStatHandle":{"DataTable":"AthenaObjectiveStatTable","RowName":"interact_athena_doorbell_tiltedtowers"},"AlternativeStatHandles":[],"ItemEvent":"EFortQuestObjectiveItemEvent::Max_None","bHidden":false,"bRequirePrimaryMissionCompletion":false,"bCanProgressInZone":true,"bDisplayDynamicAnnouncementUpdate":false,"DynamicStatusUpdateType":"EObjectiveStatusUpdateType::Always","LinkVaultTab":"EFortInventoryFilter::Max_None","LinkToItemManagement":"EFortFrontendInventoryFilter::Max_None","ItemReference":{"asset_path_name":"None","sub_path_string":""},"ItemTemplateIdOverride":"","LinkSquadID":"None","LinkSquadIndex":0,"Description":"Ring a doorbell in different named locations in a single match","HudShortDescription":"Ring a doorbell in different named locations in a single match","HudIcon":{"asset_path_name":"None","sub_path_string":""},"Count":1,"Stage":-1,"DynamicStatusUpdatePercentInterval":25,"DynamicUpdateCompletionDelay":0.0,"ScriptedAction":{"asset_path_name":"None","sub_path_string":""}},{"BackendName":"battlepass_ringdoorbell_differenthouses_poi","ObjectiveStatHandle":{"DataTable":"AthenaObjectiveStatTable","RowName":"interact_athena_doorbell_tomatotown"},"AlternativeStatHandles":[],"ItemEvent":"EFortQuestObjectiveItemEvent::Max_None","bHidden":false,"bRequirePrimaryMissionCompletion":false,"bCanProgressInZone":true,"bDisplayDynamicAnnouncementUpdate":false,"DynamicStatusUpdateType":"EObjectiveStatusUpdateType::Always","LinkVaultTab":"EFortInventoryFilter::Max_None","LinkToItemManagement":"EFortFrontendInventoryFilter::Max_None","ItemReference":{"asset_path_name":"None","sub_path_string":""},"ItemTemplateIdOverride":"","LinkSquadID":"None","LinkSquadIndex":0,"Description":"Ring a doorbell in different named locations in a single match","HudShortDescription":"Ring a doorbell in different named locations in a single match","HudIcon":{"asset_path_name":"None","sub_path_string":""},"Count":1,"Stage":-1,"DynamicStatusUpdatePercentInterval":25,"DynamicUpdateCompletionDelay":0.3,"ScriptedAction":{"asset_path_name":"None","sub_path_string":""}},{"BackendName":"battlepass_ringdoorbell_differenthouses_poi","ObjectiveStatHandle":{"DataTable":"AthenaObjectiveStatTable","RowName":"interact_athena_doorbell_wailingwoods"},"AlternativeStatHandles":[],"ItemEvent":"EFortQuestObjectiveItemEvent::Max_None","bHidden":false,"bRequirePrimaryMissionCompletion":false,"bCanProgressInZone":true,"bDisplayDynamicAnnouncementUpdate":false,"DynamicStatusUpdateType":"EObjectiveStatusUpdateType::Always","LinkVaultTab":"EFortInventoryFilter::Max_None","LinkToItemManagement":"EFortFrontendInventoryFilter::Max_None","ItemReference":{"asset_path_name":"None","sub_path_string":""},"ItemTemplateIdOverride":"","LinkSquadID":"None","LinkSquadIndex":0,"Description":"Ring a doorbell in different named locations in a single match","HudShortDescription":"Ring a doorbell in different named locations in a single match","HudIcon":{"asset_path_name":"None","sub_path_string":""},"Count":1,"Stage":-1,"DynamicStatusUpdatePercentInterval":25,"DynamicUpdateCompletionDelay":0.0,"ScriptedAction":{"asset_path_name":"None","sub_path_string":""}}],"CompletionText":"Challenge Completed!","GrantToProfileType":"athena","DisplayName":"Ring a doorbell in different named locations in a single match","Description":"Ring a doorbell in different named locations in a single match","SmallPreviewImage":{"asset_path_name":"/Game/UI/Foundation/Textures/Icons/Mission/T-Icon-Exterminate-128.T-Icon-Exterminate-128","sub_path_string":""},"LargePreviewImage":{"asset_path_name":"/Game/UI/Foundation/Textures/Icons/Mission/T-Icon-Exterminate-128.T-Icon-Exterminate-128","sub_path_string":""}}]