[{"export_type":"AthenaDanceItemDefinition","Animation":{"asset_path_name":"/Game/Animation/Game/MainPlayer/Emotes/Emote_Flex_CMM_M.Emote_Flex_CMM_M","sub_path_string":""},"EmoteCooldownSecs":1.0,"DisplayName":"Gun Show","ShortDescription":"Emote","Description":"Express yourself on the battlefield.","GameplayTags":{"gameplay_tags":["Cosmetics.EmoteType.Dance","Cosmetics.Source.ItemShop"]},"SmallPreviewImage":{"asset_path_name":"/Game/UI/Foundation/Textures/Icons/Emotes/T-Icon-Emotes-E-Flex.T-Icon-Emotes-E-Flex","sub_path_string":""},"LargePreviewImage":{"asset_path_name":"/Game/UI/Foundation/Textures/Icons/Emotes/T-Icon-Emotes-E-Flex-L.T-Icon-Emotes-E-Flex-L","sub_path_string":""}}]